Compiled from "GuiTextField.java"
public class net.minecraft.client.gui.GuiTextField extends net.minecraft.client.gui.Gui {
  private final net.minecraft.client.gui.FontRenderer field_146211_a;

  public int field_146209_f;

  public int field_146210_g;

  public int field_146218_h;

  public int field_146219_i;

  private java.lang.String field_146216_j;

  private int field_146217_k;

  private int field_146214_l;

  private boolean field_146215_m;

  private boolean field_146212_n;

  private boolean field_146213_o;

  private boolean field_146226_p;

  private int field_146225_q;

  private int field_146224_r;

  private int field_146223_s;

  private int field_146222_t;

  private int field_146221_u;

  private boolean field_146220_v;

  private static final java.lang.String __OBFID;

  public java.util.ArrayList<com.tsoft_web.IntelliInput.IMEInputText> imeInputTexts;

  public com.tsoft_web.IntelliInput.NativeStructure.CandidateList candidateList;

  private boolean isRequestAlphabetInput;

  public net.minecraft.client.gui.GuiTextField(net.minecraft.client.gui.FontRenderer, int, int, int, int);
    Code:
         0: aload_0
         1: invokespecial #45                 // Method net/minecraft/client/gui/Gui."<init>":()V
         4: aload_0
         5: ldc           #47                 // String
         7: putfield      #49                 // Field field_146216_j:Ljava/lang/String;
        10: aload_0
        11: bipush        32
        13: putfield      #51                 // Field field_146217_k:I
        16: aload_0
        17: iconst_1
        18: putfield      #53                 // Field field_146215_m:Z
        21: aload_0
        22: iconst_1
        23: putfield      #55                 // Field field_146212_n:Z
        26: aload_0
        27: iconst_1
        28: putfield      #57                 // Field field_146226_p:Z
        31: aload_0
        32: ldc           #58                 // int 14737632
        34: putfield      #60                 // Field field_146222_t:I
        37: aload_0
        38: ldc           #61                 // int 7368816
        40: putfield      #63                 // Field field_146221_u:I
        43: aload_0
        44: iconst_1
        45: putfield      #65                 // Field field_146220_v:Z
        48: getstatic     #70                 // Field com/tsoft_web/IntelliInput/IntelliInput.inputFields:Ljava/util/ArrayList;
        51: aload_0
        52: invokevirtual #76                 // Method java/util/ArrayList.add:(Ljava/lang/Object;)Z
        55: pop
        56: aload_0
        57: aload_1
        58: putfield      #78                 // Field field_146211_a:Lnet/minecraft/client/gui/FontRenderer;
        61: aload_0
        62: iload_2
        63: putfield      #80                 // Field field_146209_f:I
        66: aload_0
        67: iload_3
        68: putfield      #82                 // Field field_146210_g:I
        71: aload_0
        72: iload         4
        74: putfield      #84                 // Field field_146218_h:I
        77: aload_0
        78: iload         5
        80: putfield      #86                 // Field field_146219_i:I
        83: return

  public void func_146178_a();
    Code:
         0: aload_0
         1: dup
         2: getfield      #96                 // Field field_146214_l:I
         5: iconst_1
         6: iadd
         7: putfield      #96                 // Field field_146214_l:I
        10: return

  public void func_146180_a(java.lang.String);
    Code:
         0: aload_1
         1: invokevirtual #104                // Method java/lang/String.length:()I
         4: aload_0
         5: getfield      #51                 // Field field_146217_k:I
         8: if_icmple     27
        11: aload_0
        12: aload_1
        13: iconst_0
        14: aload_0
        15: getfield      #51                 // Field field_146217_k:I
        18: invokevirtual #108                // Method java/lang/String.substring:(II)Ljava/lang/String;
        21: putfield      #49                 // Field field_146216_j:Ljava/lang/String;
        24: goto          32
        27: aload_0
        28: aload_1
        29: putfield      #49                 // Field field_146216_j:Ljava/lang/String;
        32: aload_0
        33: invokevirtual #111                // Method func_146202_e:()V
        36: return

  public java.lang.String func_146179_b();
    Code:
         0: aload_0
         1: getfield      #49                 // Field field_146216_j:Ljava/lang/String;
         4: areturn

  public java.lang.String func_146207_c();
    Code:
         0: aload_0
         1: getfield      #117                // Field field_146224_r:I
         4: aload_0
         5: getfield      #119                // Field field_146223_s:I
         8: if_icmpge     18
        11: aload_0
        12: getfield      #117                // Field field_146224_r:I
        15: goto          22
        18: aload_0
        19: getfield      #119                // Field field_146223_s:I
        22: istore_1
        23: aload_0
        24: getfield      #117                // Field field_146224_r:I
        27: aload_0
        28: getfield      #119                // Field field_146223_s:I
        31: if_icmpge     41
        34: aload_0
        35: getfield      #119                // Field field_146223_s:I
        38: goto          45
        41: aload_0
        42: getfield      #117                // Field field_146224_r:I
        45: istore_2
        46: aload_0
        47: getfield      #49                 // Field field_146216_j:Ljava/lang/String;
        50: iload_1
        51: iload_2
        52: invokevirtual #108                // Method java/lang/String.substring:(II)Ljava/lang/String;
        55: areturn

  public void func_146191_b(java.lang.String);
    Code:
         0: ldc           #47                 // String
         2: astore_2
         3: aload_1
         4: invokestatic  #128                // Method net/minecraft/util/ChatAllowedCharacters.func_71565_a:(Ljava/lang/String;)Ljava/lang/String;
         7: astore_3
         8: aload_0
         9: getfield      #117                // Field field_146224_r:I
        12: aload_0
        13: getfield      #119                // Field field_146223_s:I
        16: if_icmpge     26
        19: aload_0
        20: getfield      #117                // Field field_146224_r:I
        23: goto          30
        26: aload_0
        27: getfield      #119                // Field field_146223_s:I
        30: istore        4
        32: aload_0
        33: getfield      #117                // Field field_146224_r:I
        36: aload_0
        37: getfield      #119                // Field field_146223_s:I
        40: if_icmpge     50
        43: aload_0
        44: getfield      #119                // Field field_146223_s:I
        47: goto          54
        50: aload_0
        51: getfield      #117                // Field field_146224_r:I
        54: istore        5
        56: aload_0
        57: getfield      #51                 // Field field_146217_k:I
        60: aload_0
        61: getfield      #49                 // Field field_146216_j:Ljava/lang/String;
        64: invokevirtual #104                // Method java/lang/String.length:()I
        67: isub
        68: iload         4
        70: aload_0
        71: getfield      #119                // Field field_146223_s:I
        74: isub
        75: isub
        76: istore        6
        78: iconst_0
        79: istore        7
        81: aload_0
        82: getfield      #49                 // Field field_146216_j:Ljava/lang/String;
        85: invokevirtual #104                // Method java/lang/String.length:()I
        88: ifle          119
        91: new           #130                // class java/lang/StringBuilder
        94: dup
        95: invokespecial #131                // Method java/lang/StringBuilder."<init>":()V
        98: aload_2
        99: invokevirtual #135                // Method java/lang/StringBuilder.append:(Ljava/lang/String;)Ljava/lang/StringBuilder;
       102: aload_0
       103: getfield      #49                 // Field field_146216_j:Ljava/lang/String;
       106: iconst_0
       107: iload         4
       109: invokevirtual #108                // Method java/lang/String.substring:(II)Ljava/lang/String;
       112: invokevirtual #135                // Method java/lang/StringBuilder.append:(Ljava/lang/String;)Ljava/lang/StringBuilder;
       115: invokevirtual #138                // Method java/lang/StringBuilder.toString:()Ljava/lang/String;
       118: astore_2
       119: iload         6
       121: aload_3
       122: invokevirtual #104                // Method java/lang/String.length:()I
       125: if_icmpge     160
       128: new           #130                // class java/lang/StringBuilder
       131: dup
       132: invokespecial #131                // Method java/lang/StringBuilder."<init>":()V
       135: aload_2
       136: invokevirtual #135                // Method java/lang/StringBuilder.append:(Ljava/lang/String;)Ljava/lang/StringBuilder;
       139: aload_3
       140: iconst_0
       141: iload         6
       143: invokevirtual #108                // Method java/lang/String.substring:(II)Ljava/lang/String;
       146: invokevirtual #135                // Method java/lang/StringBuilder.append:(Ljava/lang/String;)Ljava/lang/StringBuilder;
       149: invokevirtual #138                // Method java/lang/StringBuilder.toString:()Ljava/lang/String;
       152: astore_2
       153: iload         6
       155: istore        8
       157: goto          185
       160: new           #130                // class java/lang/StringBuilder
       163: dup
       164: invokespecial #131                // Method java/lang/StringBuilder."<init>":()V
       167: aload_2
       168: invokevirtual #135                // Method java/lang/StringBuilder.append:(Ljava/lang/String;)Ljava/lang/StringBuilder;
       171: aload_3
       172: invokevirtual #135                // Method java/lang/StringBuilder.append:(Ljava/lang/String;)Ljava/lang/StringBuilder;
       175: invokevirtual #138                // Method java/lang/StringBuilder.toString:()Ljava/lang/String;
       178: astore_2
       179: aload_3
       180: invokevirtual #104                // Method java/lang/String.length:()I
       183: istore        8
       185: aload_0
       186: getfield      #49                 // Field field_146216_j:Ljava/lang/String;
       189: invokevirtual #104                // Method java/lang/String.length:()I
       192: ifle          234
       195: iload         5
       197: aload_0
       198: getfield      #49                 // Field field_146216_j:Ljava/lang/String;
       201: invokevirtual #104                // Method java/lang/String.length:()I
       204: if_icmpge     234
       207: new           #130                // class java/lang/StringBuilder
       210: dup
       211: invokespecial #131                // Method java/lang/StringBuilder."<init>":()V
       214: aload_2
       215: invokevirtual #135                // Method java/lang/StringBuilder.append:(Ljava/lang/String;)Ljava/lang/StringBuilder;
       218: aload_0
       219: getfield      #49                 // Field field_146216_j:Ljava/lang/String;
       222: iload         5
       224: invokevirtual #141                // Method java/lang/String.substring:(I)Ljava/lang/String;
       227: invokevirtual #135                // Method java/lang/StringBuilder.append:(Ljava/lang/String;)Ljava/lang/StringBuilder;
       230: invokevirtual #138                // Method java/lang/StringBuilder.toString:()Ljava/lang/String;
       233: astore_2
       234: aload_0
       235: aload_2
       236: putfield      #49                 // Field field_146216_j:Ljava/lang/String;
       239: aload_0
       240: iload         4
       242: aload_0
       243: getfield      #119                // Field field_146223_s:I
       246: isub
       247: iload         8
       249: iadd
       250: invokevirtual #145                // Method func_146182_d:(I)V
       253: return

  public void func_146177_a(int);
    Code:
         0: aload_0
         1: getfield      #49                 // Field field_146216_j:Ljava/lang/String;
         4: invokevirtual #104                // Method java/lang/String.length:()I
         7: ifeq          44
        10: aload_0
        11: getfield      #119                // Field field_146223_s:I
        14: aload_0
        15: getfield      #117                // Field field_146224_r:I
        18: if_icmpeq     30
        21: aload_0
        22: ldc           #47                 // String
        24: invokevirtual #154                // Method func_146191_b:(Ljava/lang/String;)V
        27: goto          44
        30: aload_0
        31: aload_0
        32: iload_1
        33: invokevirtual #158                // Method func_146187_c:(I)I
        36: aload_0
        37: getfield      #117                // Field field_146224_r:I
        40: isub
        41: invokevirtual #161                // Method func_146175_b:(I)V
        44: return

  public void func_146175_b(int);
    Code:
         0: aload_0
         1: getfield      #49                 // Field field_146216_j:Ljava/lang/String;
         4: invokevirtual #104                // Method java/lang/String.length:()I
         7: ifeq          152
        10: aload_0
        11: getfield      #119                // Field field_146223_s:I
        14: aload_0
        15: getfield      #117                // Field field_146224_r:I
        18: if_icmpeq     30
        21: aload_0
        22: ldc           #47                 // String
        24: invokevirtual #154                // Method func_146191_b:(Ljava/lang/String;)V
        27: goto          152
        30: iload_1
        31: ifge          38
        34: iconst_1
        35: goto          39
        38: iconst_0
        39: istore_2
        40: iload_2
        41: ifeq          53
        44: aload_0
        45: getfield      #117                // Field field_146224_r:I
        48: iload_1
        49: iadd
        50: goto          57
        53: aload_0
        54: getfield      #117                // Field field_146224_r:I
        57: istore_3
        58: iload_2
        59: ifeq          69
        62: aload_0
        63: getfield      #117                // Field field_146224_r:I
        66: goto          75
        69: aload_0
        70: getfield      #117                // Field field_146224_r:I
        73: iload_1
        74: iadd
        75: istore        4
        77: ldc           #47                 // String
        79: astore        5
        81: iload_3
        82: iflt          96
        85: aload_0
        86: getfield      #49                 // Field field_146216_j:Ljava/lang/String;
        89: iconst_0
        90: iload_3
        91: invokevirtual #108                // Method java/lang/String.substring:(II)Ljava/lang/String;
        94: astore        5
        96: iload         4
        98: aload_0
        99: getfield      #49                 // Field field_146216_j:Ljava/lang/String;
       102: invokevirtual #104                // Method java/lang/String.length:()I
       105: if_icmpge     137
       108: new           #130                // class java/lang/StringBuilder
       111: dup
       112: invokespecial #131                // Method java/lang/StringBuilder."<init>":()V
       115: aload         5
       117: invokevirtual #135                // Method java/lang/StringBuilder.append:(Ljava/lang/String;)Ljava/lang/StringBuilder;
       120: aload_0
       121: getfield      #49                 // Field field_146216_j:Ljava/lang/String;
       124: iload         4
       126: invokevirtual #141                // Method java/lang/String.substring:(I)Ljava/lang/String;
       129: invokevirtual #135                // Method java/lang/StringBuilder.append:(Ljava/lang/String;)Ljava/lang/StringBuilder;
       132: invokevirtual #138                // Method java/lang/StringBuilder.toString:()Ljava/lang/String;
       135: astore        5
       137: aload_0
       138: aload         5
       140: putfield      #49                 // Field field_146216_j:Ljava/lang/String;
       143: iload_2
       144: ifeq          152
       147: aload_0
       148: iload_1
       149: invokevirtual #145                // Method func_146182_d:(I)V
       152: return

  public int func_146187_c(int);
    Code:
         0: aload_0
         1: iload_1
         2: aload_0
         3: invokevirtual #167                // Method func_146198_h:()I
         6: invokevirtual #171                // Method func_146183_a:(II)I
         9: ireturn

  public int func_146183_a(int, int);
    Code:
         0: aload_0
         1: iload_1
         2: aload_0
         3: invokevirtual #167                // Method func_146198_h:()I
         6: iconst_1
         7: invokevirtual #176                // Method func_146197_a:(IIZ)I
        10: ireturn

  public int func_146197_a(int, int, boolean);
    Code:
         0: iload_2
         1: istore        4
         3: iload_1
         4: ifge          11
         7: iconst_1
         8: goto          12
        11: iconst_0
        12: istore        5
        14: iload_1
        15: invokestatic  #183                // Method java/lang/Math.abs:(I)I
        18: istore        6
        20: iconst_0
        21: istore        7
        23: iload         7
        25: iload         6
        27: if_icmpge     165
        30: iload         5
        32: ifeq          93
        35: iload_3
        36: ifeq          66
        39: iload         4
        41: ifle          66
        44: aload_0
        45: getfield      #49                 // Field field_146216_j:Ljava/lang/String;
        48: iload         4
        50: iconst_1
        51: isub
        52: invokevirtual #187                // Method java/lang/String.charAt:(I)C
        55: bipush        32
        57: if_icmpne     66
        60: iinc          4, -1
        63: goto          35
        66: iload         4
        68: ifle          159
        71: aload_0
        72: getfield      #49                 // Field field_146216_j:Ljava/lang/String;
        75: iload         4
        77: iconst_1
        78: isub
        79: invokevirtual #187                // Method java/lang/String.charAt:(I)C
        82: bipush        32
        84: if_icmpeq     159
        87: iinc          4, -1
        90: goto          66
        93: aload_0
        94: getfield      #49                 // Field field_146216_j:Ljava/lang/String;
        97: invokevirtual #104                // Method java/lang/String.length:()I
       100: istore        8
       102: aload_0
       103: getfield      #49                 // Field field_146216_j:Ljava/lang/String;
       106: bipush        32
       108: iload         4
       110: invokevirtual #190                // Method java/lang/String.indexOf:(II)I
       113: istore        4
       115: iload         4
       117: iconst_m1
       118: if_icmpne     128
       121: iload         8
       123: istore        4
       125: goto          159
       128: iload_3
       129: ifeq          159
       132: iload         4
       134: iload         8
       136: if_icmpge     159
       139: aload_0
       140: getfield      #49                 // Field field_146216_j:Ljava/lang/String;
       143: iload         4
       145: invokevirtual #187                // Method java/lang/String.charAt:(I)C
       148: bipush        32
       150: if_icmpne     159
       153: iinc          4, 1
       156: goto          128
       159: iinc          7, 1
       162: goto          23
       165: iload         4
       167: ireturn

  public void func_146182_d(int);
    Code:
         0: aload_0
         1: aload_0
         2: getfield      #119                // Field field_146223_s:I
         5: iload_1
         6: iadd
         7: invokevirtual #199                // Method func_146190_e:(I)V
        10: return

  public void func_146190_e(int);
    Code:
         0: aload_0
         1: iload_1
         2: putfield      #117                // Field field_146224_r:I
         5: aload_0
         6: getfield      #49                 // Field field_146216_j:Ljava/lang/String;
         9: invokevirtual #104                // Method java/lang/String.length:()I
        12: istore_2
        13: aload_0
        14: getfield      #117                // Field field_146224_r:I
        17: ifge          25
        20: aload_0
        21: iconst_0
        22: putfield      #117                // Field field_146224_r:I
        25: aload_0
        26: getfield      #117                // Field field_146224_r:I
        29: iload_2
        30: if_icmple     38
        33: aload_0
        34: iload_2
        35: putfield      #117                // Field field_146224_r:I
        38: aload_0
        39: aload_0
        40: getfield      #117                // Field field_146224_r:I
        43: invokevirtual #203                // Method func_146199_i:(I)V
        46: return

  public void func_146196_d();
    Code:
         0: aload_0
         1: iconst_0
         2: invokevirtual #199                // Method func_146190_e:(I)V
         5: return

  public void func_146202_e();
    Code:
         0: aload_0
         1: aload_0
         2: getfield      #49                 // Field field_146216_j:Ljava/lang/String;
         5: invokevirtual #104                // Method java/lang/String.length:()I
         8: invokevirtual #199                // Method func_146190_e:(I)V
        11: return

  public boolean func_146201_a(char, int);
    Code:
         0: aload_0
         1: getfield      #209                // Field field_146213_o:Z
         4: ifne          9
         7: iconst_0
         8: ireturn
         9: iload_1
        10: lookupswitch  { // 4

                       1: 52

                       3: 63

                      22: 72

                      24: 88
                 default: 110
            }
        52: aload_0
        53: invokevirtual #111                // Method func_146202_e:()V
        56: aload_0
        57: iconst_0
        58: invokevirtual #203                // Method func_146199_i:(I)V
        61: iconst_1
        62: ireturn
        63: aload_0
        64: invokevirtual #211                // Method func_146207_c:()Ljava/lang/String;
        67: invokestatic  #216                // Method net/minecraft/client/gui/GuiScreen.func_146275_d:(Ljava/lang/String;)V
        70: iconst_1
        71: ireturn
        72: aload_0
        73: getfield      #57                 // Field field_146226_p:Z
        76: ifeq          86
        79: aload_0
        80: invokestatic  #219                // Method net/minecraft/client/gui/GuiScreen.func_146277_j:()Ljava/lang/String;
        83: invokevirtual #154                // Method func_146191_b:(Ljava/lang/String;)V
        86: iconst_1
        87: ireturn
        88: aload_0
        89: invokevirtual #211                // Method func_146207_c:()Ljava/lang/String;
        92: invokestatic  #216                // Method net/minecraft/client/gui/GuiScreen.func_146275_d:(Ljava/lang/String;)V
        95: aload_0
        96: getfield      #57                 // Field field_146226_p:Z
        99: ifeq          108
       102: aload_0
       103: ldc           #47                 // String
       105: invokevirtual #154                // Method func_146191_b:(Ljava/lang/String;)V
       108: iconst_1
       109: ireturn
       110: iload_2
       111: lookupswitch  { // 6

                      14: 168

                     199: 203

                     203: 223

                     205: 289

                     207: 355

                     211: 381
                 default: 416
            }
       168: invokestatic  #223                // Method net/minecraft/client/gui/GuiScreen.func_146271_m:()Z
       171: ifeq          189
       174: aload_0
       175: getfield      #57                 // Field field_146226_p:Z
       178: ifeq          201
       181: aload_0
       182: iconst_m1
       183: invokevirtual #225                // Method func_146177_a:(I)V
       186: goto          201
       189: aload_0
       190: getfield      #57                 // Field field_146226_p:Z
       193: ifeq          201
       196: aload_0
       197: iconst_m1
       198: invokevirtual #161                // Method func_146175_b:(I)V
       201: iconst_1
       202: ireturn
       203: invokestatic  #228                // Method net/minecraft/client/gui/GuiScreen.func_146272_n:()Z
       206: ifeq          217
       209: aload_0
       210: iconst_0
       211: invokevirtual #203                // Method func_146199_i:(I)V
       214: goto          221
       217: aload_0
       218: invokevirtual #230                // Method func_146196_d:()V
       221: iconst_1
       222: ireturn
       223: invokestatic  #228                // Method net/minecraft/client/gui/GuiScreen.func_146272_n:()Z
       226: ifeq          264
       229: invokestatic  #223                // Method net/minecraft/client/gui/GuiScreen.func_146271_m:()Z
       232: ifeq          251
       235: aload_0
       236: aload_0
       237: iconst_m1
       238: aload_0
       239: invokevirtual #233                // Method func_146186_n:()I
       242: invokevirtual #171                // Method func_146183_a:(II)I
       245: invokevirtual #203                // Method func_146199_i:(I)V
       248: goto          287
       251: aload_0
       252: aload_0
       253: invokevirtual #233                // Method func_146186_n:()I
       256: iconst_1
       257: isub
       258: invokevirtual #203                // Method func_146199_i:(I)V
       261: goto          287
       264: invokestatic  #223                // Method net/minecraft/client/gui/GuiScreen.func_146271_m:()Z
       267: ifeq          282
       270: aload_0
       271: aload_0
       272: iconst_m1
       273: invokevirtual #158                // Method func_146187_c:(I)I
       276: invokevirtual #199                // Method func_146190_e:(I)V
       279: goto          287
       282: aload_0
       283: iconst_m1
       284: invokevirtual #145                // Method func_146182_d:(I)V
       287: iconst_1
       288: ireturn
       289: invokestatic  #228                // Method net/minecraft/client/gui/GuiScreen.func_146272_n:()Z
       292: ifeq          330
       295: invokestatic  #223                // Method net/minecraft/client/gui/GuiScreen.func_146271_m:()Z
       298: ifeq          317
       301: aload_0
       302: aload_0
       303: iconst_1
       304: aload_0
       305: invokevirtual #233                // Method func_146186_n:()I
       308: invokevirtual #171                // Method func_146183_a:(II)I
       311: invokevirtual #203                // Method func_146199_i:(I)V
       314: goto          353
       317: aload_0
       318: aload_0
       319: invokevirtual #233                // Method func_146186_n:()I
       322: iconst_1
       323: iadd
       324: invokevirtual #203                // Method func_146199_i:(I)V
       327: goto          353
       330: invokestatic  #223                // Method net/minecraft/client/gui/GuiScreen.func_146271_m:()Z
       333: ifeq          348
       336: aload_0
       337: aload_0
       338: iconst_1
       339: invokevirtual #158                // Method func_146187_c:(I)I
       342: invokevirtual #199                // Method func_146190_e:(I)V
       345: goto          353
       348: aload_0
       349: iconst_1
       350: invokevirtual #145                // Method func_146182_d:(I)V
       353: iconst_1
       354: ireturn
       355: invokestatic  #228                // Method net/minecraft/client/gui/GuiScreen.func_146272_n:()Z
       358: ifeq          375
       361: aload_0
       362: aload_0
       363: getfield      #49                 // Field field_146216_j:Ljava/lang/String;
       366: invokevirtual #104                // Method java/lang/String.length:()I
       369: invokevirtual #203                // Method func_146199_i:(I)V
       372: goto          379
       375: aload_0
       376: invokevirtual #111                // Method func_146202_e:()V
       379: iconst_1
       380: ireturn
       381: invokestatic  #223                // Method net/minecraft/client/gui/GuiScreen.func_146271_m:()Z
       384: ifeq          402
       387: aload_0
       388: getfield      #57                 // Field field_146226_p:Z
       391: ifeq          414
       394: aload_0
       395: iconst_1
       396: invokevirtual #225                // Method func_146177_a:(I)V
       399: goto          414
       402: aload_0
       403: getfield      #57                 // Field field_146226_p:Z
       406: ifeq          414
       409: aload_0
       410: iconst_1
       411: invokevirtual #161                // Method func_146175_b:(I)V
       414: iconst_1
       415: ireturn
       416: iload_1
       417: invokestatic  #237                // Method net/minecraft/util/ChatAllowedCharacters.func_71566_a:(C)Z
       420: ifeq          440
       423: aload_0
       424: getfield      #57                 // Field field_146226_p:Z
       427: ifeq          438
       430: aload_0
       431: iload_1
       432: invokestatic  #242                // Method java/lang/Character.toString:(C)Ljava/lang/String;
       435: invokevirtual #154                // Method func_146191_b:(Ljava/lang/String;)V
       438: iconst_1
       439: ireturn
       440: iload_1
       441: ifne          450
       444: iload_2
       445: ifne          450
       448: iconst_1
       449: ireturn
       450: iconst_0
       451: ireturn

  public void func_146192_a(int, int, int);
    Code:
         0: iload_1
         1: aload_0
         2: getfield      #80                 // Field field_146209_f:I
         5: if_icmplt     46
         8: iload_1
         9: aload_0
        10: getfield      #80                 // Field field_146209_f:I
        13: aload_0
        14: getfield      #84                 // Field field_146218_h:I
        17: iadd
        18: if_icmpge     46
        21: iload_2
        22: aload_0
        23: getfield      #82                 // Field field_146210_g:I
        26: if_icmplt     46
        29: iload_2
        30: aload_0
        31: getfield      #82                 // Field field_146210_g:I
        34: aload_0
        35: getfield      #86                 // Field field_146219_i:I
        38: iadd
        39: if_icmpge     46
        42: iconst_1
        43: goto          47
        46: iconst_0
        47: istore        4
        49: aload_0
        50: getfield      #55                 // Field field_146212_n:Z
        53: ifeq          62
        56: aload_0
        57: iload         4
        59: invokevirtual #251                // Method func_146195_b:(Z)V
        62: aload_0
        63: getfield      #209                // Field field_146213_o:Z
        66: ifeq          138
        69: iload_3
        70: ifne          138
        73: iload_1
        74: aload_0
        75: getfield      #80                 // Field field_146209_f:I
        78: isub
        79: istore        5
        81: aload_0
        82: getfield      #53                 // Field field_146215_m:Z
        85: ifeq          91
        88: iinc          5, -4
        91: aload_0
        92: getfield      #78                 // Field field_146211_a:Lnet/minecraft/client/gui/FontRenderer;
        95: aload_0
        96: getfield      #49                 // Field field_146216_j:Ljava/lang/String;
        99: aload_0
       100: getfield      #253                // Field field_146225_q:I
       103: invokevirtual #141                // Method java/lang/String.substring:(I)Ljava/lang/String;
       106: aload_0
       107: invokevirtual #256                // Method func_146200_o:()I
       110: invokevirtual #262                // Method net/minecraft/client/gui/FontRenderer.func_78269_a:(Ljava/lang/String;I)Ljava/lang/String;
       113: astore        6
       115: aload_0
       116: aload_0
       117: getfield      #78                 // Field field_146211_a:Lnet/minecraft/client/gui/FontRenderer;
       120: aload         6
       122: iload         5
       124: invokevirtual #262                // Method net/minecraft/client/gui/FontRenderer.func_78269_a:(Ljava/lang/String;I)Ljava/lang/String;
       127: invokevirtual #104                // Method java/lang/String.length:()I
       130: aload_0
       131: getfield      #253                // Field field_146225_q:I
       134: iadd
       135: invokevirtual #199                // Method func_146190_e:(I)V
       138: return

  public void func_146194_f();
    Code:
         0: aload_0
         1: invokevirtual #269                // Method func_146176_q:()Z
         4: ifeq          553
         7: aload_0
         8: invokevirtual #272                // Method func_146181_i:()Z
        11: ifeq          86
        14: aload_0
        15: getfield      #80                 // Field field_146209_f:I
        18: iconst_1
        19: isub
        20: aload_0
        21: getfield      #82                 // Field field_146210_g:I
        24: iconst_1
        25: isub
        26: aload_0
        27: getfield      #80                 // Field field_146209_f:I
        30: aload_0
        31: getfield      #84                 // Field field_146218_h:I
        34: iadd
        35: iconst_1
        36: iadd
        37: aload_0
        38: getfield      #82                 // Field field_146210_g:I
        41: aload_0
        42: getfield      #86                 // Field field_146219_i:I
        45: iadd
        46: iconst_1
        47: iadd
        48: ldc_w         #273                // int -6250336
        51: invokestatic  #277                // Method func_73734_a:(IIIII)V
        54: aload_0
        55: getfield      #80                 // Field field_146209_f:I
        58: aload_0
        59: getfield      #82                 // Field field_146210_g:I
        62: aload_0
        63: getfield      #80                 // Field field_146209_f:I
        66: aload_0
        67: getfield      #84                 // Field field_146218_h:I
        70: iadd
        71: aload_0
        72: getfield      #82                 // Field field_146210_g:I
        75: aload_0
        76: getfield      #86                 // Field field_146219_i:I
        79: iadd
        80: ldc_w         #278                // int -16777216
        83: invokestatic  #277                // Method func_73734_a:(IIIII)V
        86: aload_0
        87: invokespecial #281                // Method getDrawText:()Ljava/lang/String;
        90: astore_1
        91: aload_0
        92: getfield      #57                 // Field field_146226_p:Z
        95: ifeq          105
        98: aload_0
        99: getfield      #60                 // Field field_146222_t:I
       102: goto          109
       105: aload_0
       106: getfield      #63                 // Field field_146221_u:I
       109: istore_2
       110: aload_0
       111: getfield      #117                // Field field_146224_r:I
       114: aload_0
       115: getfield      #253                // Field field_146225_q:I
       118: isub
       119: istore_3
       120: aload_0
       121: getfield      #119                // Field field_146223_s:I
       124: aload_0
       125: getfield      #253                // Field field_146225_q:I
       128: isub
       129: istore        4
       131: aload_0
       132: getfield      #78                 // Field field_146211_a:Lnet/minecraft/client/gui/FontRenderer;
       135: aload_1
       136: aload_0
       137: getfield      #253                // Field field_146225_q:I
       140: invokevirtual #141                // Method java/lang/String.substring:(I)Ljava/lang/String;
       143: aload_0
       144: invokevirtual #256                // Method func_146200_o:()I
       147: invokevirtual #262                // Method net/minecraft/client/gui/FontRenderer.func_78269_a:(Ljava/lang/String;I)Ljava/lang/String;
       150: astore        5
       152: iload_3
       153: iflt          169
       156: iload_3
       157: aload         5
       159: invokevirtual #104                // Method java/lang/String.length:()I
       162: if_icmpgt     169
       165: iconst_1
       166: goto          170
       169: iconst_0
       170: istore        6
       172: aload_0
       173: getfield      #209                // Field field_146213_o:Z
       176: ifeq          200
       179: aload_0
       180: getfield      #96                 // Field field_146214_l:I
       183: bipush        6
       185: idiv
       186: iconst_2
       187: irem
       188: ifne          200
       191: iload         6
       193: ifeq          200
       196: iconst_1
       197: goto          201
       200: iconst_0
       201: istore        7
       203: aload_0
       204: getfield      #53                 // Field field_146215_m:Z
       207: ifeq          219
       210: aload_0
       211: getfield      #80                 // Field field_146209_f:I
       214: iconst_4
       215: iadd
       216: goto          223
       219: aload_0
       220: getfield      #80                 // Field field_146209_f:I
       223: istore        8
       225: aload_0
       226: getfield      #53                 // Field field_146215_m:Z
       229: ifeq          249
       232: aload_0
       233: getfield      #82                 // Field field_146210_g:I
       236: aload_0
       237: getfield      #86                 // Field field_146219_i:I
       240: bipush        8
       242: isub
       243: iconst_2
       244: idiv
       245: iadd
       246: goto          253
       249: aload_0
       250: getfield      #82                 // Field field_146210_g:I
       253: istore        9
       255: iload         8
       257: istore        10
       259: iload         4
       261: aload         5
       263: invokevirtual #104                // Method java/lang/String.length:()I
       266: if_icmple     276
       269: aload         5
       271: invokevirtual #104                // Method java/lang/String.length:()I
       274: istore        4
       276: aload         5
       278: invokevirtual #104                // Method java/lang/String.length:()I
       281: ifle          319
       284: iload         6
       286: ifeq          299
       289: aload         5
       291: iconst_0
       292: iload_3
       293: invokevirtual #108                // Method java/lang/String.substring:(II)Ljava/lang/String;
       296: goto          301
       299: aload         5
       301: astore        11
       303: aload_0
       304: getfield      #78                 // Field field_146211_a:Lnet/minecraft/client/gui/FontRenderer;
       307: aload         11
       309: iload         8
       311: iload         9
       313: iload_2
       314: invokevirtual #285                // Method net/minecraft/client/gui/FontRenderer.func_78261_a:(Ljava/lang/String;III)I
       317: istore        10
       319: aload_0
       320: getfield      #117                // Field field_146224_r:I
       323: aload_0
       324: getfield      #49                 // Field field_146216_j:Ljava/lang/String;
       327: invokevirtual #104                // Method java/lang/String.length:()I
       330: if_icmplt     347
       333: aload_0
       334: getfield      #49                 // Field field_146216_j:Ljava/lang/String;
       337: invokevirtual #104                // Method java/lang/String.length:()I
       340: aload_0
       341: invokevirtual #288                // Method func_146208_g:()I
       344: if_icmplt     351
       347: iconst_1
       348: goto          352
       351: iconst_0
       352: istore        11
       354: iload         10
       356: istore        12
       358: iload         6
       360: ifne          384
       363: iload_3
       364: ifle          377
       367: iload         8
       369: aload_0
       370: getfield      #84                 // Field field_146218_h:I
       373: iadd
       374: goto          379
       377: iload         8
       379: istore        12
       381: goto          398
       384: iload         11
       386: ifeq          398
       389: iload         10
       391: iconst_1
       392: isub
       393: istore        12
       395: iinc          10, -1
       398: aload         5
       400: invokevirtual #104                // Method java/lang/String.length:()I
       403: ifle          439
       406: iload         6
       408: ifeq          439
       411: iload_3
       412: aload         5
       414: invokevirtual #104                // Method java/lang/String.length:()I
       417: if_icmpge     439
       420: aload_0
       421: getfield      #78                 // Field field_146211_a:Lnet/minecraft/client/gui/FontRenderer;
       424: aload         5
       426: iload_3
       427: invokevirtual #141                // Method java/lang/String.substring:(I)Ljava/lang/String;
       430: iload         10
       432: iload         9
       434: iload_2
       435: invokevirtual #285                // Method net/minecraft/client/gui/FontRenderer.func_78261_a:(Ljava/lang/String;III)I
       438: pop
       439: iload         7
       441: ifeq          496
       444: iload         11
       446: ifeq          480
       449: iload         12
       451: iload         9
       453: iconst_1
       454: isub
       455: iload         12
       457: iconst_1
       458: iadd
       459: iload         9
       461: iconst_1
       462: iadd
       463: aload_0
       464: getfield      #78                 // Field field_146211_a:Lnet/minecraft/client/gui/FontRenderer;
       467: getfield      #291                // Field net/minecraft/client/gui/FontRenderer.field_78288_b:I
       470: iadd
       471: ldc_w         #292                // int -3092272
       474: invokestatic  #293                // Method net/minecraft/client/gui/Gui.func_73734_a:(IIIII)V
       477: goto          496
       480: aload_0
       481: getfield      #78                 // Field field_146211_a:Lnet/minecraft/client/gui/FontRenderer;
       484: ldc_w         #295                // String _
       487: iload         12
       489: iload         9
       491: iload_2
       492: invokevirtual #285                // Method net/minecraft/client/gui/FontRenderer.func_78261_a:(Ljava/lang/String;III)I
       495: pop
       496: aload_0
       497: aload_1
       498: invokespecial #298                // Method drawCandidateList:(Ljava/lang/String;)V
       501: iload         4
       503: iload_3
       504: if_icmpeq     553
       507: iload         8
       509: aload_0
       510: getfield      #78                 // Field field_146211_a:Lnet/minecraft/client/gui/FontRenderer;
       513: aload         5
       515: iconst_0
       516: iload         4
       518: invokevirtual #108                // Method java/lang/String.substring:(II)Ljava/lang/String;
       521: invokevirtual #302                // Method net/minecraft/client/gui/FontRenderer.func_78256_a:(Ljava/lang/String;)I
       524: iadd
       525: istore        13
       527: aload_0
       528: iload         12
       530: iload         9
       532: iconst_1
       533: isub
       534: iload         13
       536: iconst_1
       537: isub
       538: iload         9
       540: iconst_1
       541: iadd
       542: aload_0
       543: getfield      #78                 // Field field_146211_a:Lnet/minecraft/client/gui/FontRenderer;
       546: getfield      #291                // Field net/minecraft/client/gui/FontRenderer.field_78288_b:I
       549: iadd
       550: invokespecial #306                // Method func_146188_c:(IIII)V
       553: return

  private void func_146188_c(int, int, int, int);
    Code:
         0: iload_1
         1: iload_3
         2: if_icmpge     13
         5: iload_1
         6: istore        5
         8: iload_3
         9: istore_1
        10: iload         5
        12: istore_3
        13: iload_2
        14: iload         4
        16: if_icmpge     29
        19: iload_2
        20: istore        5
        22: iload         4
        24: istore_2
        25: iload         5
        27: istore        4
        29: iload_3
        30: aload_0
        31: getfield      #80                 // Field field_146209_f:I
        34: aload_0
        35: getfield      #84                 // Field field_146218_h:I
        38: iadd
        39: if_icmple     52
        42: aload_0
        43: getfield      #80                 // Field field_146209_f:I
        46: aload_0
        47: getfield      #84                 // Field field_146218_h:I
        50: iadd
        51: istore_3
        52: iload_1
        53: aload_0
        54: getfield      #80                 // Field field_146209_f:I
        57: aload_0
        58: getfield      #84                 // Field field_146218_h:I
        61: iadd
        62: if_icmple     75
        65: aload_0
        66: getfield      #80                 // Field field_146209_f:I
        69: aload_0
        70: getfield      #84                 // Field field_146218_h:I
        73: iadd
        74: istore_1
        75: getstatic     #316                // Field net/minecraft/client/renderer/Tessellator.field_78398_a:Lnet/minecraft/client/renderer/Tessellator;
        78: astore        6
        80: fconst_0
        81: fconst_0
        82: ldc_w         #317                // float 255.0f
        85: ldc_w         #317                // float 255.0f
        88: invokestatic  #323                // Method org/lwjgl/opengl/GL11.glColor4f:(FFFF)V
        91: sipush        3553
        94: invokestatic  #326                // Method org/lwjgl/opengl/GL11.glDisable:(I)V
        97: sipush        3058
       100: invokestatic  #329                // Method org/lwjgl/opengl/GL11.glEnable:(I)V
       103: sipush        5387
       106: invokestatic  #332                // Method org/lwjgl/opengl/GL11.glLogicOp:(I)V
       109: aload         6
       111: invokevirtual #335                // Method net/minecraft/client/renderer/Tessellator.func_78382_b:()V
       114: aload         6
       116: iload_1
       117: i2d
       118: iload         4
       120: i2d
       121: dconst_0
       122: invokevirtual #339                // Method net/minecraft/client/renderer/Tessellator.func_78377_a:(DDD)V
       125: aload         6
       127: iload_3
       128: i2d
       129: iload         4
       131: i2d
       132: dconst_0
       133: invokevirtual #339                // Method net/minecraft/client/renderer/Tessellator.func_78377_a:(DDD)V
       136: aload         6
       138: iload_3
       139: i2d
       140: iload_2
       141: i2d
       142: dconst_0
       143: invokevirtual #339                // Method net/minecraft/client/renderer/Tessellator.func_78377_a:(DDD)V
       146: aload         6
       148: iload_1
       149: i2d
       150: iload_2
       151: i2d
       152: dconst_0
       153: invokevirtual #339                // Method net/minecraft/client/renderer/Tessellator.func_78377_a:(DDD)V
       156: aload         6
       158: invokevirtual #342                // Method net/minecraft/client/renderer/Tessellator.func_78381_a:()I
       161: pop
       162: sipush        3058
       165: invokestatic  #326                // Method org/lwjgl/opengl/GL11.glDisable:(I)V
       168: sipush        3553
       171: invokestatic  #329                // Method org/lwjgl/opengl/GL11.glEnable:(I)V
       174: return

  public void func_146203_f(int);
    Code:
         0: aload_0
         1: iload_1
         2: putfield      #51                 // Field field_146217_k:I
         5: aload_0
         6: getfield      #49                 // Field field_146216_j:Ljava/lang/String;
         9: invokevirtual #104                // Method java/lang/String.length:()I
        12: iload_1
        13: if_icmple     29
        16: aload_0
        17: aload_0
        18: getfield      #49                 // Field field_146216_j:Ljava/lang/String;
        21: iconst_0
        22: iload_1
        23: invokevirtual #108                // Method java/lang/String.substring:(II)Ljava/lang/String;
        26: putfield      #49                 // Field field_146216_j:Ljava/lang/String;
        29: return

  public int func_146208_g();
    Code:
         0: aload_0
         1: getfield      #51                 // Field field_146217_k:I
         4: ireturn

  public int func_146198_h();
    Code:
         0: aload_0
         1: getfield      #117                // Field field_146224_r:I
         4: ireturn

  public boolean func_146181_i();
    Code:
         0: aload_0
         1: getfield      #53                 // Field field_146215_m:Z
         4: ireturn

  public void func_146185_a(boolean);
    Code:
         0: aload_0
         1: iload_1
         2: putfield      #53                 // Field field_146215_m:Z
         5: return

  public void func_146193_g(int);
    Code:
         0: aload_0
         1: iload_1
         2: putfield      #60                 // Field field_146222_t:I
         5: return

  public void func_146204_h(int);
    Code:
         0: aload_0
         1: iload_1
         2: putfield      #63                 // Field field_146221_u:I
         5: return

  public void func_146195_b(boolean);
    Code:
         0: iload_1
         1: ifeq          16
         4: aload_0
         5: getfield      #209                // Field field_146213_o:Z
         8: ifne          16
        11: aload_0
        12: iconst_0
        13: putfield      #96                 // Field field_146214_l:I
        16: aload_0
        17: iload_1
        18: putfield      #209                // Field field_146213_o:Z
        21: return

  public boolean func_146206_l();
    Code:
         0: aload_0
         1: getfield      #209                // Field field_146213_o:Z
         4: ireturn

  public void func_146184_c(boolean);
    Code:
         0: aload_0
         1: iload_1
         2: putfield      #57                 // Field field_146226_p:Z
         5: return

  public int func_146186_n();
    Code:
         0: aload_0
         1: getfield      #119                // Field field_146223_s:I
         4: ireturn

  public int func_146200_o();
    Code:
         0: aload_0
         1: invokevirtual #272                // Method func_146181_i:()Z
         4: ifeq          17
         7: aload_0
         8: getfield      #84                 // Field field_146218_h:I
        11: bipush        8
        13: isub
        14: goto          21
        17: aload_0
        18: getfield      #84                 // Field field_146218_h:I
        21: ireturn

  public void func_146199_i(int);
    Code:
         0: aload_0
         1: getfield      #49                 // Field field_146216_j:Ljava/lang/String;
         4: invokevirtual #104                // Method java/lang/String.length:()I
         7: istore_2
         8: iload_1
         9: iload_2
        10: if_icmple     15
        13: iload_2
        14: istore_1
        15: iload_1
        16: ifge          21
        19: iconst_0
        20: istore_1
        21: aload_0
        22: iload_1
        23: putfield      #119                // Field field_146223_s:I
        26: aload_0
        27: getfield      #78                 // Field field_146211_a:Lnet/minecraft/client/gui/FontRenderer;
        30: ifnull        187
        33: aload_0
        34: getfield      #253                // Field field_146225_q:I
        37: iload_2
        38: if_icmple     46
        41: aload_0
        42: iload_2
        43: putfield      #253                // Field field_146225_q:I
        46: aload_0
        47: invokevirtual #256                // Method func_146200_o:()I
        50: istore_3
        51: aload_0
        52: getfield      #78                 // Field field_146211_a:Lnet/minecraft/client/gui/FontRenderer;
        55: aload_0
        56: getfield      #49                 // Field field_146216_j:Ljava/lang/String;
        59: aload_0
        60: getfield      #253                // Field field_146225_q:I
        63: invokevirtual #141                // Method java/lang/String.substring:(I)Ljava/lang/String;
        66: iload_3
        67: invokevirtual #262                // Method net/minecraft/client/gui/FontRenderer.func_78269_a:(Ljava/lang/String;I)Ljava/lang/String;
        70: astore        4
        72: aload         4
        74: invokevirtual #104                // Method java/lang/String.length:()I
        77: aload_0
        78: getfield      #253                // Field field_146225_q:I
        81: iadd
        82: istore        5
        84: iload_1
        85: aload_0
        86: getfield      #253                // Field field_146225_q:I
        89: if_icmpne     117
        92: aload_0
        93: dup
        94: getfield      #253                // Field field_146225_q:I
        97: aload_0
        98: getfield      #78                 // Field field_146211_a:Lnet/minecraft/client/gui/FontRenderer;
       101: aload_0
       102: getfield      #49                 // Field field_146216_j:Ljava/lang/String;
       105: iload_3
       106: iconst_1
       107: invokevirtual #363                // Method net/minecraft/client/gui/FontRenderer.func_78262_a:(Ljava/lang/String;IZ)Ljava/lang/String;
       110: invokevirtual #104                // Method java/lang/String.length:()I
       113: isub
       114: putfield      #253                // Field field_146225_q:I
       117: iload_1
       118: iload         5
       120: if_icmple     139
       123: aload_0
       124: dup
       125: getfield      #253                // Field field_146225_q:I
       128: iload_1
       129: iload         5
       131: isub
       132: iadd
       133: putfield      #253                // Field field_146225_q:I
       136: goto          162
       139: iload_1
       140: aload_0
       141: getfield      #253                // Field field_146225_q:I
       144: if_icmpgt     162
       147: aload_0
       148: dup
       149: getfield      #253                // Field field_146225_q:I
       152: aload_0
       153: getfield      #253                // Field field_146225_q:I
       156: iload_1
       157: isub
       158: isub
       159: putfield      #253                // Field field_146225_q:I
       162: aload_0
       163: getfield      #253                // Field field_146225_q:I
       166: ifge          174
       169: aload_0
       170: iconst_0
       171: putfield      #253                // Field field_146225_q:I
       174: aload_0
       175: getfield      #253                // Field field_146225_q:I
       178: iload_2
       179: if_icmple     187
       182: aload_0
       183: iload_2
       184: putfield      #253                // Field field_146225_q:I
       187: return

  public void func_146205_d(boolean);
    Code:
         0: aload_0
         1: iload_1
         2: putfield      #55                 // Field field_146212_n:Z
         5: return

  public boolean func_146176_q();
    Code:
         0: aload_0
         1: getfield      #65                 // Field field_146220_v:Z
         4: ireturn

  public void func_146189_e(boolean);
    Code:
         0: aload_0
         1: iload_1
         2: putfield      #65                 // Field field_146220_v:Z
         5: return

  private java.lang.String getDrawText();
    Code:
         0: aload_0
         1: getfield      #49                 // Field field_146216_j:Ljava/lang/String;
         4: astore_1
         5: aload_0
         6: getfield      #370                // Field imeInputTexts:Ljava/util/ArrayList;
         9: ifnull        251
        12: aload_0
        13: getfield      #370                // Field imeInputTexts:Ljava/util/ArrayList;
        16: invokevirtual #373                // Method java/util/ArrayList.size:()I
        19: ifeq          251
        22: aload_1
        23: invokevirtual #104                // Method java/lang/String.length:()I
        26: aload_0
        27: invokevirtual #167                // Method func_146198_h:()I
        30: if_icmplt     199
        33: aload_0
        34: getfield      #117                // Field field_146224_r:I
        37: aload_0
        38: getfield      #119                // Field field_146223_s:I
        41: if_icmpge     51
        44: aload_0
        45: getfield      #117                // Field field_146224_r:I
        48: goto          55
        51: aload_0
        52: getfield      #119                // Field field_146223_s:I
        55: istore_2
        56: aload_0
        57: getfield      #117                // Field field_146224_r:I
        60: aload_0
        61: getfield      #119                // Field field_146223_s:I
        64: if_icmpge     74
        67: aload_0
        68: getfield      #119                // Field field_146223_s:I
        71: goto          78
        74: aload_0
        75: getfield      #117                // Field field_146224_r:I
        78: istore_3
        79: aload_0
        80: getfield      #117                // Field field_146224_r:I
        83: aload_0
        84: getfield      #119                // Field field_146223_s:I
        87: if_icmple     100
        90: aload_0
        91: iload_2
        92: putfield      #117                // Field field_146224_r:I
        95: aload_0
        96: iload_3
        97: putfield      #119                // Field field_146223_s:I
       100: aload_1
       101: iconst_0
       102: iload_2
       103: invokevirtual #108                // Method java/lang/String.substring:(II)Ljava/lang/String;
       106: astore_1
       107: aload_0
       108: getfield      #370                // Field imeInputTexts:Ljava/util/ArrayList;
       111: invokevirtual #377                // Method java/util/ArrayList.iterator:()Ljava/util/Iterator;
       114: astore        4
       116: aload         4
       118: invokeinterface #382,  1          // InterfaceMethod java/util/Iterator.hasNext:()Z
       123: ifeq          164
       126: aload         4
       128: invokeinterface #386,  1          // InterfaceMethod java/util/Iterator.next:()Ljava/lang/Object;
       133: checkcast     #388                // class com/tsoft_web/IntelliInput/IMEInputText
       136: astore        5
       138: new           #130                // class java/lang/StringBuilder
       141: dup
       142: invokespecial #131                // Method java/lang/StringBuilder."<init>":()V
       145: aload_1
       146: invokevirtual #135                // Method java/lang/StringBuilder.append:(Ljava/lang/String;)Ljava/lang/StringBuilder;
       149: aload         5
       151: invokevirtual #391                // Method com/tsoft_web/IntelliInput/IMEInputText.getFormatString:()Ljava/lang/String;
       154: invokevirtual #135                // Method java/lang/StringBuilder.append:(Ljava/lang/String;)Ljava/lang/StringBuilder;
       157: invokevirtual #138                // Method java/lang/StringBuilder.toString:()Ljava/lang/String;
       160: astore_1
       161: goto          116
       164: new           #130                // class java/lang/StringBuilder
       167: dup
       168: invokespecial #131                // Method java/lang/StringBuilder."<init>":()V
       171: aload_1
       172: invokevirtual #135                // Method java/lang/StringBuilder.append:(Ljava/lang/String;)Ljava/lang/StringBuilder;
       175: ldc_w         #393                // String ��r
       178: invokevirtual #135                // Method java/lang/StringBuilder.append:(Ljava/lang/String;)Ljava/lang/StringBuilder;
       181: aload_0
       182: getfield      #49                 // Field field_146216_j:Ljava/lang/String;
       185: iload_3
       186: invokevirtual #141                // Method java/lang/String.substring:(I)Ljava/lang/String;
       189: invokevirtual #135                // Method java/lang/StringBuilder.append:(Ljava/lang/String;)Ljava/lang/StringBuilder;
       192: invokevirtual #138                // Method java/lang/StringBuilder.toString:()Ljava/lang/String;
       195: astore_1
       196: goto          251
       199: aload_0
       200: getfield      #370                // Field imeInputTexts:Ljava/util/ArrayList;
       203: invokevirtual #377                // Method java/util/ArrayList.iterator:()Ljava/util/Iterator;
       206: astore_2
       207: aload_2
       208: invokeinterface #382,  1          // InterfaceMethod java/util/Iterator.hasNext:()Z
       213: ifeq          251
       216: aload_2
       217: invokeinterface #386,  1          // InterfaceMethod java/util/Iterator.next:()Ljava/lang/Object;
       222: checkcast     #388                // class com/tsoft_web/IntelliInput/IMEInputText
       225: astore_3
       226: new           #130                // class java/lang/StringBuilder
       229: dup
       230: invokespecial #131                // Method java/lang/StringBuilder."<init>":()V
       233: aload_1
       234: invokevirtual #135                // Method java/lang/StringBuilder.append:(Ljava/lang/String;)Ljava/lang/StringBuilder;
       237: aload_3
       238: invokevirtual #391                // Method com/tsoft_web/IntelliInput/IMEInputText.getFormatString:()Ljava/lang/String;
       241: invokevirtual #135                // Method java/lang/StringBuilder.append:(Ljava/lang/String;)Ljava/lang/StringBuilder;
       244: invokevirtual #138                // Method java/lang/StringBuilder.toString:()Ljava/lang/String;
       247: astore_1
       248: goto          207
       251: aload_1
       252: areturn

  private void drawCandidateList(java.lang.String);
    Code:
         0: aload_0
         1: getfield      #397                // Field candidateList:Lcom/tsoft_web/IntelliInput/NativeStructure/CandidateList;
         4: ifnull        38
         7: aload_0
         8: aload_0
         9: getfield      #78                 // Field field_146211_a:Lnet/minecraft/client/gui/FontRenderer;
        12: aload_0
        13: getfield      #397                // Field candidateList:Lcom/tsoft_web/IntelliInput/NativeStructure/CandidateList;
        16: aload_1
        17: aload_0
        18: getfield      #80                 // Field field_146209_f:I
        21: aload_0
        22: getfield      #82                 // Field field_146210_g:I
        25: aload_0
        26: getfield      #82                 // Field field_146210_g:I
        29: aload_0
        30: getfield      #86                 // Field field_146219_i:I
        33: iadd
        34: iconst_0
        35: invokestatic  #403                // Method com/tsoft_web/IntelliInput/IntelliInputRenderer.renderCandidateList:(Lnet/minecraft/client/gui/Gui;Lnet/minecraft/client/gui/FontRenderer;Lcom/tsoft_web/IntelliInput/NativeStructure/CandidateList;Ljava/lang/String;IIIZ)V
        38: return

  public boolean isEnabled();
    Code:
         0: aload_0
         1: getfield      #57                 // Field field_146226_p:Z
         4: ireturn

  public void setRequestAlphabetInput(boolean);
    Code:
         0: aload_0
         1: iload_1
         2: putfield      #407                // Field isRequestAlphabetInput:Z
         5: return

  public boolean isRequestAlphabetInput();
    Code:
         0: aload_0
         1: getfield      #407                // Field isRequestAlphabetInput:Z
         4: ireturn
}
