Compiled from "IMEInputText.java"
public class com.tsoft_web.IntelliInput.IMEInputText {
  public com.tsoft_web.IntelliInput.IMEAttribute attribute;

  public java.lang.String text;

  public com.tsoft_web.IntelliInput.IMEInputText(com.tsoft_web.IntelliInput.IMEAttribute, java.lang.String);
    Code:
         0: aload_0
         1: invokespecial #14                 // Method java/lang/Object."<init>":()V
         4: aload_0
         5: aload_1
         6: putfield      #16                 // Field attribute:Lcom/tsoft_web/IntelliInput/IMEAttribute;
         9: aload_0
        10: aload_2
        11: invokestatic  #22                 // Method com/tsoft_web/IntelliInput/IntelliInput.Sanitizing:(Ljava/lang/String;)Ljava/lang/String;
        14: putfield      #24                 // Field text:Ljava/lang/String;
        17: return

  public java.lang.String toString();
    Code:
         0: new           #30                 // class java/lang/StringBuilder
         3: dup
         4: invokespecial #31                 // Method java/lang/StringBuilder."<init>":()V
         7: aload_0
         8: getfield      #24                 // Field text:Ljava/lang/String;
        11: invokevirtual #35                 // Method java/lang/StringBuilder.append:(Ljava/lang/String;)Ljava/lang/StringBuilder;
        14: ldc           #37                 // String  /
        16: invokevirtual #35                 // Method java/lang/StringBuilder.append:(Ljava/lang/String;)Ljava/lang/StringBuilder;
        19: aload_0
        20: getfield      #16                 // Field attribute:Lcom/tsoft_web/IntelliInput/IMEAttribute;
        23: invokevirtual #41                 // Method com/tsoft_web/IntelliInput/IMEAttribute.toString:()Ljava/lang/String;
        26: invokevirtual #35                 // Method java/lang/StringBuilder.append:(Ljava/lang/String;)Ljava/lang/StringBuilder;
        29: invokevirtual #42                 // Method java/lang/StringBuilder.toString:()Ljava/lang/String;
        32: areturn

  public java.lang.String getFormatString(boolean);
    Code:
         0: ldc           #46                 // String
         2: astore_2
         3: aload_0
         4: getfield      #16                 // Field attribute:Lcom/tsoft_web/IntelliInput/IMEAttribute;
         7: getstatic     #49                 // Field com/tsoft_web/IntelliInput/IMEAttribute.ATTR_INPUT:Lcom/tsoft_web/IntelliInput/IMEAttribute;
        10: if_acmpeq     143
        13: aload_0
        14: getfield      #16                 // Field attribute:Lcom/tsoft_web/IntelliInput/IMEAttribute;
        17: getstatic     #52                 // Field com/tsoft_web/IntelliInput/IMEAttribute.ATTR_TARGET_NOTCONVERTED:Lcom/tsoft_web/IntelliInput/IMEAttribute;
        20: if_acmpne     26
        23: goto          143
        26: aload_0
        27: getfield      #16                 // Field attribute:Lcom/tsoft_web/IntelliInput/IMEAttribute;
        30: getstatic     #57                 // Field com/tsoft_web/IntelliInput/IMEAttribute.ATTR_TARGET_CONVERTED:Lcom/tsoft_web/IntelliInput/IMEAttribute;
        33: if_acmpne     86
        36: iload_1
        37: ifeq          63
        40: new           #30                 // class java/lang/StringBuilder
        43: dup
        44: invokespecial #31                 // Method java/lang/StringBuilder."<init>":()V
        47: aload_2
        48: invokevirtual #35                 // Method java/lang/StringBuilder.append:(Ljava/lang/String;)Ljava/lang/StringBuilder;
        51: ldc           #59                 // String ��8
        53: invokevirtual #35                 // Method java/lang/StringBuilder.append:(Ljava/lang/String;)Ljava/lang/StringBuilder;
        56: invokevirtual #42                 // Method java/lang/StringBuilder.toString:()Ljava/lang/String;
        59: astore_2
        60: goto          143
        63: new           #30                 // class java/lang/StringBuilder
        66: dup
        67: invokespecial #31                 // Method java/lang/StringBuilder."<init>":()V
        70: aload_2
        71: invokevirtual #35                 // Method java/lang/StringBuilder.append:(Ljava/lang/String;)Ljava/lang/StringBuilder;
        74: ldc           #61                 // String ��f
        76: invokevirtual #35                 // Method java/lang/StringBuilder.append:(Ljava/lang/String;)Ljava/lang/StringBuilder;
        79: invokevirtual #42                 // Method java/lang/StringBuilder.toString:()Ljava/lang/String;
        82: astore_2
        83: goto          143
        86: aload_0
        87: getfield      #16                 // Field attribute:Lcom/tsoft_web/IntelliInput/IMEAttribute;
        90: getstatic     #64                 // Field com/tsoft_web/IntelliInput/IMEAttribute.ATTR_CONVERTED:Lcom/tsoft_web/IntelliInput/IMEAttribute;
        93: if_acmpne     143
        96: iload_1
        97: ifeq          123
       100: new           #30                 // class java/lang/StringBuilder
       103: dup
       104: invokespecial #31                 // Method java/lang/StringBuilder."<init>":()V
       107: aload_2
       108: invokevirtual #35                 // Method java/lang/StringBuilder.append:(Ljava/lang/String;)Ljava/lang/StringBuilder;
       111: ldc           #66                 // String ��7
       113: invokevirtual #35                 // Method java/lang/StringBuilder.append:(Ljava/lang/String;)Ljava/lang/StringBuilder;
       116: invokevirtual #42                 // Method java/lang/StringBuilder.toString:()Ljava/lang/String;
       119: astore_2
       120: goto          143
       123: new           #30                 // class java/lang/StringBuilder
       126: dup
       127: invokespecial #31                 // Method java/lang/StringBuilder."<init>":()V
       130: aload_2
       131: invokevirtual #35                 // Method java/lang/StringBuilder.append:(Ljava/lang/String;)Ljava/lang/StringBuilder;
       134: ldc           #66                 // String ��7
       136: invokevirtual #35                 // Method java/lang/StringBuilder.append:(Ljava/lang/String;)Ljava/lang/StringBuilder;
       139: invokevirtual #42                 // Method java/lang/StringBuilder.toString:()Ljava/lang/String;
       142: astore_2
       143: new           #30                 // class java/lang/StringBuilder
       146: dup
       147: invokespecial #31                 // Method java/lang/StringBuilder."<init>":()V
       150: aload_2
       151: invokevirtual #35                 // Method java/lang/StringBuilder.append:(Ljava/lang/String;)Ljava/lang/StringBuilder;
       154: ldc           #68                 // String ��n
       156: invokevirtual #35                 // Method java/lang/StringBuilder.append:(Ljava/lang/String;)Ljava/lang/StringBuilder;
       159: aload_0
       160: getfield      #24                 // Field text:Ljava/lang/String;
       163: invokevirtual #35                 // Method java/lang/StringBuilder.append:(Ljava/lang/String;)Ljava/lang/StringBuilder;
       166: invokevirtual #42                 // Method java/lang/StringBuilder.toString:()Ljava/lang/String;
       169: astore_2
       170: aload_2
       171: areturn

  public java.lang.String getFormatString();
    Code:
         0: aload_0
         1: iconst_0
         2: invokevirtual #73                 // Method getFormatString:(Z)Ljava/lang/String;
         5: areturn
}
