Compiled from "IntelliInputRenderer.java"
public class com.tsoft_web.IntelliInput.IntelliInputRenderer {
  private static final int DEFAULT_PAGE_SIZE;

  public static final java.lang.String[] colorCodesStrings;

  public static final int[] colorCodesInts;

  public com.tsoft_web.IntelliInput.IntelliInputRenderer();
    Code:
         0: aload_0
         1: invokespecial #16                 // Method java/lang/Object."<init>":()V
         4: return

  public static void renderCandidateList(net.minecraft.client.gui.Gui, net.minecraft.client.gui.FontRenderer, com.tsoft_web.IntelliInput.NativeStructure.CandidateList, java.lang.String, int, int, int, boolean, int);
    Code:
         0: iload         8
         2: istore        9
         4: invokestatic  #26                 // Method net/minecraft/client/Minecraft.func_71410_x:()Lnet/minecraft/client/Minecraft;
         7: getfield      #30                 // Field net/minecraft/client/Minecraft.field_71462_r:Lnet/minecraft/client/gui/GuiScreen;
        10: getfield      #35                 // Field net/minecraft/client/gui/GuiScreen.field_146294_l:I
        13: istore        10
        15: invokestatic  #26                 // Method net/minecraft/client/Minecraft.func_71410_x:()Lnet/minecraft/client/Minecraft;
        18: getfield      #30                 // Field net/minecraft/client/Minecraft.field_71462_r:Lnet/minecraft/client/gui/GuiScreen;
        21: getfield      #38                 // Field net/minecraft/client/gui/GuiScreen.field_146295_m:I
        24: istore        11
        26: aload_1
        27: getfield      #43                 // Field net/minecraft/client/gui/FontRenderer.field_78288_b:I
        30: iload         9
        32: imul
        33: istore        12
        35: aload_2
        36: getfield      #48                 // Field com/tsoft_web/IntelliInput/NativeStructure/CandidateList.dwSelection:I
        39: ifne          48
        42: iconst_0
        43: istore        13
        45: goto          57
        48: aload_2
        49: getfield      #48                 // Field com/tsoft_web/IntelliInput/NativeStructure/CandidateList.dwSelection:I
        52: iload         9
        54: idiv
        55: istore        13
        57: iload         12
        59: iload         6
        61: iadd
        62: iload         11
        64: if_icmpge     73
        67: iconst_1
        68: istore        14
        70: goto          90
        73: iload         5
        75: iload         12
        77: isub
        78: iflt          87
        81: iconst_0
        82: istore        14
        84: goto          90
        87: iconst_1
        88: istore        14
        90: iconst_m1
        91: istore        16
        93: iload         7
        95: ifeq          259
        98: aload_3
        99: invokevirtual #56                 // Method java/lang/String.length:()I
       102: istore        15
       104: aload_1
       105: aload_3
       106: bipush        116
       108: invokevirtual #60                 // Method net/minecraft/client/gui/FontRenderer.func_78271_c:(Ljava/lang/String;I)Ljava/util/List;
       111: astore        17
       113: iload         5
       115: aload_1
       116: getfield      #43                 // Field net/minecraft/client/gui/FontRenderer.field_78288_b:I
       119: iadd
       120: istore        5
       122: aload         17
       124: invokeinterface #65,  1           // InterfaceMethod java/util/List.size:()I
       129: iconst_1
       130: isub
       131: istore        18
       133: iload         18
       135: iflt          252
       138: aload         17
       140: iload         18
       142: invokeinterface #69,  2           // InterfaceMethod java/util/List.get:(I)Ljava/lang/Object;
       147: invokevirtual #73                 // Method java/lang/Object.toString:()Ljava/lang/String;
       150: ldc           #75                 // String ��8��n
       152: invokevirtual #79                 // Method java/lang/String.lastIndexOf:(Ljava/lang/String;)I
       155: istore        19
       157: iload         19
       159: iconst_m1
       160: if_icmpeq     199
       163: iload         18
       165: istore        16
       167: iload         19
       169: istore        15
       171: aload         17
       173: iload         16
       175: invokeinterface #69,  2           // InterfaceMethod java/util/List.get:(I)Ljava/lang/Object;
       180: invokevirtual #73                 // Method java/lang/Object.toString:()Ljava/lang/String;
       183: astore_3
       184: iload         5
       186: iload         16
       188: aload_1
       189: getfield      #43                 // Field net/minecraft/client/gui/FontRenderer.field_78288_b:I
       192: imul
       193: iadd
       194: istore        5
       196: goto          252
       199: iload         18
       201: ifne          246
       204: aload         17
       206: invokeinterface #65,  1           // InterfaceMethod java/util/List.size:()I
       211: iconst_1
       212: isub
       213: istore        16
       215: aload         17
       217: iload         16
       219: invokeinterface #69,  2           // InterfaceMethod java/util/List.get:(I)Ljava/lang/Object;
       224: invokevirtual #73                 // Method java/lang/Object.toString:()Ljava/lang/String;
       227: astore_3
       228: aload_3
       229: invokevirtual #56                 // Method java/lang/String.length:()I
       232: istore        15
       234: iload         5
       236: iload         16
       238: aload_1
       239: getfield      #43                 // Field net/minecraft/client/gui/FontRenderer.field_78288_b:I
       242: imul
       243: iadd
       244: istore        5
       246: iinc          18, -1
       249: goto          133
       252: iload         5
       254: istore        6
       256: goto          286
       259: aload_3
       260: ldc           #81                 // String ��f��n
       262: invokevirtual #79                 // Method java/lang/String.lastIndexOf:(Ljava/lang/String;)I
       265: istore        17
       267: iload         17
       269: iconst_m1
       270: if_icmpne     282
       273: aload_3
       274: invokevirtual #56                 // Method java/lang/String.length:()I
       277: istore        15
       279: goto          286
       282: iload         17
       284: istore        15
       286: iload         4
       288: aload_1
       289: aload_3
       290: iconst_0
       291: iload         15
       293: invokevirtual #85                 // Method java/lang/String.substring:(II)Ljava/lang/String;
       296: invokevirtual #88                 // Method net/minecraft/client/gui/FontRenderer.func_78256_a:(Ljava/lang/String;)I
       299: iadd
       300: istore        17
       302: iconst_0
       303: istore        18
       305: aload_2
       306: getfield      #92                 // Field com/tsoft_web/IntelliInput/NativeStructure/CandidateList.list:Ljava/util/ArrayList;
       309: invokevirtual #95                 // Method java/util/ArrayList.size:()I
       312: istore        20
       314: iconst_0
       315: istore        19
       317: iload         19
       319: iload         9
       321: if_icmpgt     379
       324: iload         13
       326: iload         9
       328: imul
       329: iload         19
       331: iadd
       332: istore        21
       334: iload         21
       336: iload         20
       338: if_icmplt     344
       341: goto          379
       344: aload_1
       345: aload_2
       346: getfield      #92                 // Field com/tsoft_web/IntelliInput/NativeStructure/CandidateList.list:Ljava/util/ArrayList;
       349: iload         21
       351: invokevirtual #96                 // Method java/util/ArrayList.get:(I)Ljava/lang/Object;
       354: checkcast     #52                 // class java/lang/String
       357: invokevirtual #88                 // Method net/minecraft/client/gui/FontRenderer.func_78256_a:(Ljava/lang/String;)I
       360: istore        22
       362: iload         22
       364: iload         18
       366: if_icmple     373
       369: iload         22
       371: istore        18
       373: iinc          19, 1
       376: goto          317
       379: iload         14
       381: ifeq          554
       384: iload         17
       386: iload         6
       388: iload         17
       390: iload         18
       392: iadd
       393: iconst_2
       394: iadd
       395: iload         6
       397: iload         12
       399: iadd
       400: iconst_1
       401: iadd
       402: ldc           #97                 // int -6250336
       404: invokestatic  #101                // Method net/minecraft/client/gui/Gui.func_73734_a:(IIIII)V
       407: iload         17
       409: iconst_1
       410: iadd
       411: iload         6
       413: iconst_1
       414: iadd
       415: iload         17
       417: iload         18
       419: iadd
       420: iload         6
       422: iload         12
       424: iadd
       425: iconst_m1
       426: invokestatic  #101                // Method net/minecraft/client/gui/Gui.func_73734_a:(IIIII)V
       429: iconst_0
       430: istore        19
       432: iload         19
       434: iload         9
       436: if_icmpge     735
       439: iload         13
       441: iload         9
       443: imul
       444: iload         19
       446: iadd
       447: istore        21
       449: iload         21
       451: iload         20
       453: if_icmplt     459
       456: goto          735
       459: aload_2
       460: getfield      #48                 // Field com/tsoft_web/IntelliInput/NativeStructure/CandidateList.dwSelection:I
       463: iload         21
       465: if_icmpne     508
       468: iload         17
       470: iconst_1
       471: iadd
       472: iload         6
       474: iconst_1
       475: iadd
       476: iload         19
       478: aload_1
       479: getfield      #43                 // Field net/minecraft/client/gui/FontRenderer.field_78288_b:I
       482: imul
       483: iadd
       484: iload         17
       486: iload         18
       488: iadd
       489: iload         6
       491: iconst_1
       492: iadd
       493: iload         19
       495: iconst_1
       496: iadd
       497: aload_1
       498: getfield      #43                 // Field net/minecraft/client/gui/FontRenderer.field_78288_b:I
       501: imul
       502: iadd
       503: ldc           #102                // int -3413770
       505: invokestatic  #101                // Method net/minecraft/client/gui/Gui.func_73734_a:(IIIII)V
       508: aload_1
       509: aload_2
       510: getfield      #92                 // Field com/tsoft_web/IntelliInput/NativeStructure/CandidateList.list:Ljava/util/ArrayList;
       513: iload         13
       515: iload         9
       517: imul
       518: iload         19
       520: iadd
       521: invokevirtual #96                 // Method java/util/ArrayList.get:(I)Ljava/lang/Object;
       524: checkcast     #52                 // class java/lang/String
       527: iload         17
       529: iconst_1
       530: iadd
       531: iload         6
       533: iconst_1
       534: iadd
       535: iload         19
       537: aload_1
       538: getfield      #43                 // Field net/minecraft/client/gui/FontRenderer.field_78288_b:I
       541: imul
       542: iadd
       543: iconst_0
       544: invokevirtual #106                // Method net/minecraft/client/gui/FontRenderer.func_78276_b:(Ljava/lang/String;III)I
       547: pop
       548: iinc          19, 1
       551: goto          432
       554: iload         17
       556: iload         5
       558: iload         17
       560: iload         18
       562: iadd
       563: iconst_2
       564: iadd
       565: iload         5
       567: iload         12
       569: isub
       570: iconst_3
       571: isub
       572: ldc           #97                 // int -6250336
       574: invokestatic  #101                // Method net/minecraft/client/gui/Gui.func_73734_a:(IIIII)V
       577: iload         17
       579: iconst_1
       580: iadd
       581: iload         5
       583: iconst_1
       584: isub
       585: iload         17
       587: iload         18
       589: iadd
       590: iload         5
       592: iload         12
       594: isub
       595: iconst_2
       596: isub
       597: iconst_m1
       598: invokestatic  #101                // Method net/minecraft/client/gui/Gui.func_73734_a:(IIIII)V
       601: iconst_0
       602: istore        19
       604: iload         19
       606: iload         9
       608: if_icmpge     735
       611: iload         13
       613: iload         9
       615: imul
       616: iload         19
       618: iadd
       619: istore        21
       621: iload         21
       623: iload         20
       625: if_icmplt     631
       628: goto          735
       631: aload_2
       632: getfield      #48                 // Field com/tsoft_web/IntelliInput/NativeStructure/CandidateList.dwSelection:I
       635: iload         21
       637: if_icmpne     686
       640: iload         17
       642: iconst_1
       643: iadd
       644: iload         5
       646: iconst_1
       647: isub
       648: iload         9
       650: iload         19
       652: isub
       653: iconst_1
       654: isub
       655: aload_1
       656: getfield      #43                 // Field net/minecraft/client/gui/FontRenderer.field_78288_b:I
       659: imul
       660: isub
       661: iload         17
       663: iload         18
       665: iadd
       666: iload         5
       668: iconst_1
       669: isub
       670: iload         9
       672: iload         19
       674: isub
       675: aload_1
       676: getfield      #43                 // Field net/minecraft/client/gui/FontRenderer.field_78288_b:I
       679: imul
       680: isub
       681: ldc           #102                // int -3413770
       683: invokestatic  #101                // Method net/minecraft/client/gui/Gui.func_73734_a:(IIIII)V
       686: aload_1
       687: aload_2
       688: getfield      #92                 // Field com/tsoft_web/IntelliInput/NativeStructure/CandidateList.list:Ljava/util/ArrayList;
       691: iload         13
       693: iload         9
       695: imul
       696: iload         19
       698: iadd
       699: invokevirtual #96                 // Method java/util/ArrayList.get:(I)Ljava/lang/Object;
       702: checkcast     #52                 // class java/lang/String
       705: iload         17
       707: iconst_1
       708: iadd
       709: iload         5
       711: iconst_1
       712: isub
       713: iload         9
       715: iload         19
       717: isub
       718: aload_1
       719: getfield      #43                 // Field net/minecraft/client/gui/FontRenderer.field_78288_b:I
       722: imul
       723: isub
       724: iconst_0
       725: invokevirtual #106                // Method net/minecraft/client/gui/FontRenderer.func_78276_b:(Ljava/lang/String;III)I
       728: pop
       729: iinc          19, 1
       732: goto          604
       735: return

  public static void renderCandidateList(net.minecraft.client.gui.Gui, net.minecraft.client.gui.FontRenderer, com.tsoft_web.IntelliInput.NativeStructure.CandidateList, java.lang.String, int, int, int, boolean);
    Code:
         0: aload_0
         1: aload_1
         2: aload_2
         3: aload_3
         4: iload         4
         6: iload         5
         8: iload         6
        10: iload         7
        12: iconst_3
        13: invokestatic  #139                // Method renderCandidateList:(Lnet/minecraft/client/gui/Gui;Lnet/minecraft/client/gui/FontRenderer;Lcom/tsoft_web/IntelliInput/NativeStructure/CandidateList;Ljava/lang/String;IIIZI)V
        16: return

  private static int countStringInString(java.lang.String, java.lang.String);
    Code:
         0: aload_0
         1: invokevirtual #56                 // Method java/lang/String.length:()I
         4: aload_0
         5: aload_1
         6: ldc           #143                // String
         8: invokevirtual #147                // Method java/lang/String.replaceAll:(Ljava/lang/String;Ljava/lang/String;)Ljava/lang/String;
        11: invokevirtual #56                 // Method java/lang/String.length:()I
        14: isub
        15: aload_1
        16: invokevirtual #56                 // Method java/lang/String.length:()I
        19: idiv
        20: ireturn

  public static void renderColorPalette(int, int, net.minecraft.client.gui.Gui, java.util.List<net.minecraft.client.gui.GuiButton>, boolean);
    Code:
         0: iconst_0
         1: istore        5
         3: iload         5
         5: getstatic     #153                // Field colorCodesStrings:[Ljava/lang/String;
         8: arraylength
         9: if_icmpge     203
        12: iload         5
        14: bipush        16
        16: if_icmplt     57
        19: new           #155                // class java/lang/StringBuilder
        22: dup
        23: invokespecial #156                // Method java/lang/StringBuilder."<init>":()V
        26: ldc           #158                // String ��f��
        28: invokevirtual #162                // Method java/lang/StringBuilder.append:(Ljava/lang/String;)Ljava/lang/StringBuilder;
        31: getstatic     #153                // Field colorCodesStrings:[Ljava/lang/String;
        34: iload         5
        36: aaload
        37: invokevirtual #162                // Method java/lang/StringBuilder.append:(Ljava/lang/String;)Ljava/lang/StringBuilder;
        40: getstatic     #153                // Field colorCodesStrings:[Ljava/lang/String;
        43: iload         5
        45: aaload
        46: invokevirtual #162                // Method java/lang/StringBuilder.append:(Ljava/lang/String;)Ljava/lang/StringBuilder;
        49: invokevirtual #163                // Method java/lang/StringBuilder.toString:()Ljava/lang/String;
        52: astore        6
        54: goto          88
        57: new           #155                // class java/lang/StringBuilder
        60: dup
        61: invokespecial #156                // Method java/lang/StringBuilder."<init>":()V
        64: ldc           #165                // String ��
        66: invokevirtual #162                // Method java/lang/StringBuilder.append:(Ljava/lang/String;)Ljava/lang/StringBuilder;
        69: getstatic     #153                // Field colorCodesStrings:[Ljava/lang/String;
        72: iload         5
        74: aaload
        75: invokevirtual #162                // Method java/lang/StringBuilder.append:(Ljava/lang/String;)Ljava/lang/StringBuilder;
        78: ldc           #167                // String ��
        80: invokevirtual #162                // Method java/lang/StringBuilder.append:(Ljava/lang/String;)Ljava/lang/StringBuilder;
        83: invokevirtual #163                // Method java/lang/StringBuilder.toString:()Ljava/lang/String;
        86: astore        6
        88: iload         5
        90: bipush        10
        92: if_icmplt     136
        95: iload_0
        96: bipush        30
        98: isub
        99: istore        7
       101: iload         4
       103: ifeq          120
       106: bipush        32
       108: iload         5
       110: bipush        10
       112: isub
       113: bipush        16
       115: imul
       116: iadd
       117: goto          131
       120: bipush        10
       122: iload         5
       124: bipush        10
       126: isub
       127: bipush        16
       129: imul
       130: iadd
       131: istore        8
       133: goto          168
       136: iload_0
       137: bipush        55
       139: isub
       140: istore        7
       142: iload         4
       144: ifeq          158
       147: bipush        32
       149: iload         5
       151: bipush        16
       153: imul
       154: iadd
       155: goto          166
       158: bipush        10
       160: iload         5
       162: bipush        16
       164: imul
       165: iadd
       166: istore        8
       168: aload_3
       169: new           #169                // class net/minecraft/client/gui/GuiButton
       172: dup
       173: bipush        100
       175: iload         5
       177: iadd
       178: iload         7
       180: iload         8
       182: bipush        20
       184: bipush        16
       186: aload         6
       188: invokespecial #172                // Method net/minecraft/client/gui/GuiButton."<init>":(IIIIILjava/lang/String;)V
       191: invokeinterface #176,  2          // InterfaceMethod java/util/List.add:(Ljava/lang/Object;)Z
       196: pop
       197: iinc          5, 1
       200: goto          3
       203: return

  static {};
    Code:
         0: bipush        22
         2: anewarray     #52                 // class java/lang/String
         5: dup
         6: iconst_0
         7: ldc           #185                // String 0
         9: aastore
        10: dup
        11: iconst_1
        12: ldc           #187                // String 1
        14: aastore
        15: dup
        16: iconst_2
        17: ldc           #189                // String 2
        19: aastore
        20: dup
        21: iconst_3
        22: ldc           #191                // String 3
        24: aastore
        25: dup
        26: iconst_4
        27: ldc           #193                // String 4
        29: aastore
        30: dup
        31: iconst_5
        32: ldc           #195                // String 5
        34: aastore
        35: dup
        36: bipush        6
        38: ldc           #197                // String 6
        40: aastore
        41: dup
        42: bipush        7
        44: ldc           #199                // String 7
        46: aastore
        47: dup
        48: bipush        8
        50: ldc           #201                // String 8
        52: aastore
        53: dup
        54: bipush        9
        56: ldc           #203                // String 9
        58: aastore
        59: dup
        60: bipush        10
        62: ldc           #205                // String a
        64: aastore
        65: dup
        66: bipush        11
        68: ldc           #207                // String b
        70: aastore
        71: dup
        72: bipush        12
        74: ldc           #209                // String c
        76: aastore
        77: dup
        78: bipush        13
        80: ldc           #211                // String d
        82: aastore
        83: dup
        84: bipush        14
        86: ldc           #213                // String e
        88: aastore
        89: dup
        90: bipush        15
        92: ldc           #215                // String f
        94: aastore
        95: dup
        96: bipush        16
        98: ldc           #217                // String k
       100: aastore
       101: dup
       102: bipush        17
       104: ldc           #219                // String l
       106: aastore
       107: dup
       108: bipush        18
       110: ldc           #221                // String m
       112: aastore
       113: dup
       114: bipush        19
       116: ldc           #223                // String n
       118: aastore
       119: dup
       120: bipush        20
       122: ldc           #225                // String o
       124: aastore
       125: dup
       126: bipush        21
       128: ldc           #227                // String r
       130: aastore
       131: putstatic     #153                // Field colorCodesStrings:[Ljava/lang/String;
       134: bipush        22
       136: newarray       int
       138: dup
       139: iconst_0
       140: ldc           #228                // int -16777216
       142: iastore
       143: dup
       144: iconst_1
       145: ldc           #229                // int -16777046
       147: iastore
       148: dup
       149: iconst_2
       150: ldc           #230                // int -16733696
       152: iastore
       153: dup
       154: iconst_3
       155: ldc           #231                // int -16733526
       157: iastore
       158: dup
       159: iconst_4
       160: ldc           #232                // int -5636096
       162: iastore
       163: dup
       164: iconst_5
       165: ldc           #233                // int -5635926
       167: iastore
       168: dup
       169: bipush        6
       171: sipush        -22016
       174: iastore
       175: dup
       176: bipush        7
       178: ldc           #234                // int -5592406
       180: iastore
       181: dup
       182: bipush        8
       184: ldc           #235                // int -11184811
       186: iastore
       187: dup
       188: bipush        9
       190: ldc           #236                // int -11184641
       192: iastore
       193: dup
       194: bipush        10
       196: ldc           #237                // int -11141291
       198: iastore
       199: dup
       200: bipush        11
       202: ldc           #238                // int -11141121
       204: iastore
       205: dup
       206: bipush        12
       208: ldc           #239                // int -43691
       210: iastore
       211: dup
       212: bipush        13
       214: ldc           #240                // int -43521
       216: iastore
       217: dup
       218: bipush        14
       220: sipush        -171
       223: iastore
       224: dup
       225: bipush        15
       227: iconst_m1
       228: iastore
       229: dup
       230: bipush        16
       232: iconst_m1
       233: iastore
       234: dup
       235: bipush        17
       237: iconst_m1
       238: iastore
       239: dup
       240: bipush        18
       242: iconst_m1
       243: iastore
       244: dup
       245: bipush        19
       247: iconst_m1
       248: iastore
       249: dup
       250: bipush        20
       252: iconst_m1
       253: iastore
       254: dup
       255: bipush        21
       257: iconst_m1
       258: iastore
       259: putstatic     #242                // Field colorCodesInts:[I
       262: return
}
